Metadata-Version: 2.1
Name: odoo-addon-sale_line_refund_to_invoice_qty
Version: 18.0.1.0.0.3
Requires-Python: >=3.10
Requires-Dist: odoo==18.0.*
Requires-Dist: openupgradelib
Summary: Allow deciding whether refunded quantity should be considered as quantity to reinvoice
Home-page: https://github.com/OCA/account-invoicing
License: LGPL-3
Author: ForgeFlow, Odoo Community Association (OCA)
Author-email: support@odoo-community.org
Classifier: Programming Language :: Python
Classifier: Framework :: Odoo
Classifier: Framework :: Odoo :: 18.0
Classifier: License :: OSI Approved :: GNU Lesser General Public License v3 (LGPLv3)
